testbenchexecutor/__init__.py
testbenchexecutor/__main__.py
testbenchexecutor/tb_report_generator.py
testbenchexecutor/test_load_tb_manifest.py
testbenchexecutor/test_parse.py
testbenchexecutor/progress_service/__init__.py
testbenchexecutor/progress_service/gen/__init__.py
testbenchexecutor/progress_service/gen/progress_feedback_pb2.py
testbenchexecutor/progress_service/gen/progress_feedback_pb2_grpc.py
testbenchexecutor/templates/__init__.py
testbenchexecutor/templates/normalize.css
testbenchexecutor/templates/report.html
testbenchexecutor/templates/styles.css
testbenchexecutor-0.1.12.dist-info/METADATA
testbenchexecutor-0.1.12.dist-info/WHEEL
testbenchexecutor-0.1.12.dist-info/entry_points.txt
testbenchexecutor-0.1.12.dist-info/top_level.txt
testbenchexecutor-0.1.12.dist-info/RECORD
