Metadata-Version: 2.1
Name: testbenchexecutor
Version: 0.1.12
Summary: Executes the steps in a Test Bench manifest
Author: MetaMorph Software, Inc
Author-email: adam.nagel@gmail.com
Project-URL: Source, https://github.com/metamorph-inc/testbenchexecutor
Requires-Dist: python-dateutil >=2.5.0
Requires-Dist: Jinja2 >=2.10.0
